looker_deployer/__init__.py
looker_deployer/cli.py
looker_deployer/version.py
looker_deployer/commands/__init__.py
looker_deployer/commands/deploy_boards.py
looker_deployer/commands/deploy_code.py
looker_deployer/commands/deploy_connections.py
looker_deployer/commands/deploy_content.py
looker_deployer/commands/deploy_content_export.py
looker_deployer/commands/deploy_group_in_group.py
looker_deployer/commands/deploy_groups.py
looker_deployer/commands/deploy_model_sets.py
looker_deployer/commands/deploy_permission_sets.py
looker_deployer/commands/deploy_role_to_group.py
looker_deployer/commands/deploy_roles.py
looker_deployer/commands/deploy_user_attributes.py
looker_deployer/utils/__init__.py
looker_deployer/utils/deploy_logging.py
looker_deployer/utils/get_client.py
looker_deployer/utils/match_by_key.py
looker_deployer/utils/parse_ini.py
looker_deployer-0.3.12.dist-info/LICENSE.txt
looker_deployer-0.3.12.dist-info/METADATA
looker_deployer-0.3.12.dist-info/WHEEL
looker_deployer-0.3.12.dist-info/entry_points.txt
looker_deployer-0.3.12.dist-info/top_level.txt
looker_deployer-0.3.12.dist-info/RECORD
