Metadata-Version: 2.1
Name: looker-deployer
Version: 0.3.12
Summary: A Looker Deployment Tool
Home-page: UNKNOWN
Author: Looker Open Source
Author-email: looker-open-source@google.com
License: Apache License 2.0
Keywords: Looker Deployer
Platform: UNKNOWN
Requires-Python: >=3.6.0, <3.11
License-File: LICENSE.txt
Requires-Dist: looker-sdk>=21.18.0
Requires-Dist: oyaml
Requires-Dist: python-json-logger
